{"name":"shaking-effect","className":"DataModel","filePaths":["default.project.json"],"children":[{"name":"StarterPlayer","className":"StarterPlayer","children":[{"name":"StarterPlayerScripts","className":"StarterPlayerScripts","children":[{"name":"DialogueClientScript","className":"LocalScript","children":[{"name":"Effects","className":"Folder","children":[{"name":"ShakingEffect","className":"ModuleScript","filePaths":["src\\init.lua"],"children":[{"name":"ShakingContainer","className":"ModuleScript","filePaths":["src\\ShakingContainer.lua"]}]}]}]}]}]}]}